{
 "filename": [
  "scity509.zip"
 ],
 "files": {
  "scity509.bsp": {
   "size": 1737080,
   "timestamp": "2011-01-10T11:23:34.000Z"
  },
  "scity509.txt": {
   "size": 202,
   "timestamp": "2011-01-10T22:16:28.000Z"
  }
 },
 "filesize": 679,
 "install": {
  "extract": "{quake}/id1/maps"
 },
 "json_version": "2019.12.24-13.03",
 "sha256": "89ac3be8eff12882b598af9061e4679a33234e2f6b9ff1a32f97cf440e5e2229",
 "tags": [
  "author=NCMark",
  "game=quake",
  "releasedate=2011-01-10",
  "tag=city",
  "tag=medium",
  "tag=realism",
  "tag=sewers",
  "title=Quake City"
 ],
 "urls": [
  "https://www.quaddicted.com/filebase/scity509.zip",
  "https://www.quaddicted.com/files/by-sha256/8/89ac3be8eff12882b598af9061e4679a33234e2f6b9ff1a32f97cf440e5e2229/scity509.zip"
 ]
}