{
 "filename": [
  "sthangar.zip"
 ],
 "files": {
  "sthangar/gnu.txt": {
   "filesize": 14969,
   "timestamp": "1999-12-21"
  },
  "sthangar/pak0.pak": {
   "filesize": 8389617,
   "timestamp": "2018-05-02"
  },
  "sthangar/quake+miscmodels.fgd": {
   "filesize": 18515,
   "timestamp": "2017-11-11"
  },
  "sthangar/sthangar.TXT": {
   "filesize": 11408,
   "timestamp": "2018-05-02"
  },
  "sthangar/sthangar.map": {
   "filesize": 3716039,
   "timestamp": "2018-05-02"
  },
  "sthangar/sthangarqc.zip": {
   "filesize": 107073,
   "timestamp": "2018-05-02"
  }
 },
 "filesize": 3669,
 "install": {
  "extract": "{quake}//"
 },
 "json_version": "2019.12.23-19.15",
 "sha256": "8fe3d61a0e046478541287ed19c5704d20a5926f1ec904c154b98f28e1b01243",
 "tags": [
  "title:The Subterrestrial Hangar",
  "releasedate:2018-05-02",
  "game:quake",
  "commandline:-game sthangar",
  "author:Esrael",
  "tag:small",
  "tag:base",
  "tag:realism",
  "tag:routes",
  "tag:models",
  "tag:limits",
  "tag:source",
  "tag:maze",
  "tag:slime",
  "tag:multiple exits",
  "tag:dm"
 ],
 "urls": [
  "https://www.quaddicted.com/filebase/sthangar.zip",
  "https://www.quaddicted.com/files/by-sha256/8/8fe3d61a0e046478541287ed19c5704d20a5926f1ec904c154b98f28e1b01243/sthangar.zip"
 ]
}