{
 "version": "20191222-0",
 "sha256": "3059acd2ccc3316fd12fe8565c9d42a5f4acde068654ffb6fa506bbf5ecc78dc",
 "filename": [
  "digs04.zip"
 ],
 "size": 3302,
 "releasedate": "2008-06-18",
 "tags": [
  "title:The Parallel Worlds",
  "author:Digs",
  "tag:base",
  "tag:idbase",
  "tag:multiple playthrough map",
  "tag:large",
  "tag:mustplay",
  "tag:unique",
  "tag:ikbase"
 ],
 "install": {
  "extract": "{quake}/id1/maps/"
 },
 "files": {
  "digs04.txt": {
   "size": 1607,
   "timestamp": "2008-06-17"
  },
  "digs04.bsp": {
   "size": 8112560,
   "timestamp": "2008-06-18"
  }
 },
 "urls": [
  "https://www.quaddicted.com/filebase/digs04.zip",
  "https://www.quaddicted.com/files/by-sha256/3/3059acd2ccc3316fd12fe8565c9d42a5f4acde068654ffb6fa506bbf5ecc78dc/digs04.zip"
 ]
}