{
 "filename": [
  "initial.zip"
 ],
 "files": {
  "initial.bsp": {
   "size": 1107036,
   "timestamp": "1996-10-13T15:39:18.000Z"
  },
  "initial.txt": {
   "size": 2015,
   "timestamp": "1996-10-13T18:16:10.000Z"
  }
 },
 "filesize": 482,
 "install": {
  "extract": "{quake}/id1/maps/"
 },
 "json_version": "2019.12.24-13.03",
 "sha256": "f0a655d794d80aa37281e90c6e99f592a970b93001d2caf8842b332e50896c55",
 "tags": [
  "author=David Jewsbury",
  "game=quake",
  "link=[Crash's](http://www.quake2.com/crash/levelsi.htm)",
  "releasedate=1996-10-13",
  "tag=medium",
  "tag=mixtex",
  "title=Initial Horror"
 ],
 "urls": [
  "https://www.quaddicted.com/filebase/initial.zip",
  "https://www.quaddicted.com/files/by-sha256/f/f0a655d794d80aa37281e90c6e99f592a970b93001d2caf8842b332e50896c55/initial.zip"
 ]
}