{
 "filename": [
  "cmc.zip"
 ],
 "files": {
  "CMC.bsp": {
   "size": 4401960,
   "timestamp": "2004-11-22T21:05:48.000Z"
  },
  "CMC.lit": {
   "size": 1801073,
   "timestamp": "2004-11-22T21:05:48.000Z"
  },
  "CMC.txt": {
   "size": 2700,
   "timestamp": "2004-11-21T10:42:32.000Z"
  }
 },
 "filesize": 1970,
 "install": {
  "extract": "{quake}/id1/maps/"
 },
 "json_version": "2019.12.24-13.03",
 "sha256": "fba24bd9bd3c63313ac1d7a3ff664cb984f366d98f900bf45c9700b706e8b6e2",
 "tags": [
  "author=JPL",
  "game=quake",
  "link=[Underworldfan's](/webarchive/underworld.planetquake.gamespy.com/quakerev050107.html)",
  "link=[erc's Quality](http://qexpo.tastyspleen.net/booth.php?id=155&amp;page=283)",
  "releasedate=2004-11-20",
  "tag=base",
  "tag=industrial",
  "tag=large",
  "tag=textures",
  "tag=underground",
  "title=Cheyenne Mountain Complex"
 ],
 "urls": [
  "https://www.quaddicted.com/filebase/cmc.zip",
  "https://www.quaddicted.com/files/by-sha256/f/fba24bd9bd3c63313ac1d7a3ff664cb984f366d98f900bf45c9700b706e8b6e2/cmc.zip"
 ]
}