{
 "bytes": 826,
 "files": {
  "sm28.bsp": {
   "bytes": 2098316,
   "sha256": "830605307423c4c3f823d09ebf785869a3b463db9fc86c2298400bfc46e33976",
   "timestamp": "2001-08-26T00:02:58.000Z"
  },
  "sm28.txt": {
   "bytes": 2895,
   "sha256": "a6528e399885c177ac1d4d1d77b9aae100b0df7f7ae1ee5203e23398c816b313",
   "timestamp": "2001-08-26T00:08:14.000Z"
  }
 },
 "install": {
  "extract": "{base}/id1/maps/"
 },
 "json_version": "2023.11.06-23.20",
 "sha256": "793f55b177e6d97835a56e008f4b1a42a01cace24566501bfc80b7e494e7ea04",
 "tags": [
  "author=DaMaul",
  "author=Lunaran",
  "author=Xenon",
  "author=than",
  "filename=sm28_pack.zip",
  "game=quake",
  "game_mode=singleplayer",
  "release_date=2001-08-26",
  "startmap=sm28",
  "title=Speedmapping pack 28 - Chain map",
  "type=chainmap",
  "type=speedmap"
 ],
 "urls": [
  "https://www.quaddicted.com/filebase/sm28_pack.zip",
  "https://www.quaddicted.com/files/by-sha256/79/793f55b177e6d97835a56e008f4b1a42a01cace24566501bfc80b7e494e7ea04/sm28_pack.zip"
 ]
}
