{
 "version": "20191222-0",
 "sha256": "bc9b18bda3739f0900edcfef40630600d026aee06fd10ee9b01d6af91d96a28d",
 "filename": [
  "bldstone.zip"
 ],
 "size": 457,
 "releasedate": "1997-02-06",
 "tags": [
  "title:Bloodstone",
  "author:Drakkon (C.D. Roberts)",
  "tag:medium",
  "tag:mixtex",
  "startmap:bldston"
 ],
 "install": {
  "extract": "{quake}/id1/maps/"
 },
 "files": {
  "bldston.bsp": {
   "size": 1045356,
   "timestamp": "1997-01-18"
  },
  "bldston.txt": {
   "size": 1671,
   "timestamp": "1997-02-06"
  }
 },
 "urls": [
  "https://www.quaddicted.com/filebase/bldstone.zip",
  "https://www.quaddicted.com/files/by-sha256/b/bc9b18bda3739f0900edcfef40630600d026aee06fd10ee9b01d6af91d96a28d/bldstone.zip"
 ]
}