{
 "filename": [
  "frcastle.zip"
 ],
 "files": {
  "frcastle.TXT": {
   "sha256": "02d628dc529282806e292e04555d1d6a5519f0e61d62067cc5fb8391623f4fd7",
   "size": 788,
   "timestamp": "1996-10-24T23:17:00.000Z"
  },
  "frcastle.bsp": {
   "sha256": "150778a634539cb95bd4493296c9a92d10d98ec472e45cee2e0878a60457b464",
   "size": 780860,
   "timestamp": "1996-10-24T22:57:26.000Z"
  }
 },
 "filesize": 321,
 "install": {
  "extract": "{quake}/id1/maps/"
 },
 "json_version": "2019.12.24-12.08",
 "sha256": "be747ef75bce8076acffa72172beee964ab26869d7e666c67ba0f08efdf3363e",
 "tags": [
  "author=Robert Carter",
  "game=quake",
  "link=[Crash's](http://www.quake2.com/crash/levelsf.htm#fcastle)",
  "releasedate=1996-10-24",
  "tag=castle",
  "tag=dark",
  "tag=dm",
  "tag=old version",
  "tag=small",
  "tag=wizard",
  "title=Fear Castle"
 ],
 "urls": [
  "https://www.quaddicted.com/filebase/frcastle.zip",
  "https://www.quaddicted.com/files/by-sha256/b/be747ef75bce8076acffa72172beee964ab26869d7e666c67ba0f08efdf3363e/frcastle.zip"
 ]
}