{
 "filename": [
  "sm115_pack.zip"
 ],
 "files": {
  "sm115_bam.bsp": {
   "filesize": 218944,
   "timestamp": "2005-12-17"
  },
  "sm115_generic.bsp": {
   "filesize": 525996,
   "timestamp": "2005-12-20"
  },
  "sm115_neg!ke.bsp": {
   "filesize": 1055960,
   "timestamp": "2005-12-18"
  },
  "sm115_pack.txt": {
   "filesize": 1351,
   "timestamp": "2005-12-20"
  }
 },
 "filesize": 571,
 "install": {
  "extract": "{quake}/id1/maps/"
 },
 "json_version": "2019.12.23-19.15",
 "sha256": "c5371643c56e4f6f13a38ebad05c6210bdb17dbf5840e1dfce482f70a40d2634",
 "tags": [
  "title:Speedmapping pack 115 - Ziggurat",
  "releasedate:2005-12-20",
  "game:quake",
  "author:bambuz",
  "author:generic",
  "author:negke",
  "startmap:sm115_bam",
  "startmap:sm115_neg!ke",
  "startmap:sm115_generic"
 ],
 "urls": [
  "https://www.quaddicted.com/filebase/sm115_pack.zip",
  "https://www.quaddicted.com/files/by-sha256/c/c5371643c56e4f6f13a38ebad05c6210bdb17dbf5840e1dfce482f70a40d2634/sm115_pack.zip"
 ]
}