{
 "version": "20191222-0",
 "sha256": "c9eec35edc240b5d362029504ac6e16243d9842ab9659c10b3d98e0d43aca4aa",
 "filename": [
  "anoxia.zip"
 ],
 "size": 174,
 "releasedate": "1996-08-31",
 "tags": [
  "title:ANOXIA",
  "author:Paul Cook",
  "tag:small",
  "tag:mixtex",
  "tag:crap",
  "tag:no exit",
  "tag:classic"
 ],
 "install": {
  "extract": "{quake}/id1/maps/"
 },
 "files": {
  "ANOXIA.BSP": {
   "size": 386268,
   "timestamp": "1996-08-31"
  },
  "ANOXIA.TXT": {
   "size": 1423,
   "timestamp": "1996-08-31"
  }
 },
 "urls": [
  "https://www.quaddicted.com/filebase/anoxia.zip",
  "https://www.quaddicted.com/files/by-sha256/c/c9eec35edc240b5d362029504ac6e16243d9842ab9659c10b3d98e0d43aca4aa/anoxia.zip"
 ]
}