{
 "version": "20191222-0",
 "md5": "2bc88d07f3a95a7f2b00ad65e2ab2ea9",
 "filename": [
  "arenaq.zip"
 ],
 "size": 293,
 "releasedate": "1997-01-09",
 "tags": [
  "title:Arenaq",
  "author:Bad Ash",
  "tag:large",
  "tag:base",
  "tag:room",
  "tag:crap",
  "tag:no exit",
  "tag:source",
  "tag:arena"
 ],
 "install": {
  "extract": "{quake}/id1/maps/"
 },
 "files": {
  "arena3.h2": {
   "size": 3472,
   "timestamp": "1997-01-09"
  },
  "arena3.MAP": {
   "size": 16543,
   "timestamp": "1997-01-09"
  },
  "arenaq.txt": {
   "size": 2184,
   "timestamp": "1997-01-09"
  },
  "arena3.h1": {
   "size": 3105,
   "timestamp": "1997-01-09"
  },
  "arena3.prt": {
   "size": 12517,
   "timestamp": "1997-01-09"
  },
  "arena3.bsp": {
   "size": 918764,
   "timestamp": "1997-01-09"
  }
 }
}