{
 "version": "20191222-0",
 "sha256": "c9b7c8c78b0808972a2ca7055df3ba1898f8004d1cc34f09ae1f0f9042889a4e",
 "filename": [
  "dmc2.zip"
 ],
 "size": 2418,
 "releasedate": "2011-05-12",
 "tags": [
  "title:Deathmatch Classics Vol. 2",
  "author:Connor Fitzgerald feat. Biff Debris",
  "author:inertia",
  "author:Evan Wagner",
  "author:Kell",
  "tag:episode",
  "tag:small",
  "tag:base",
  "tag:metal",
  "tag:rubicon",
  "tag:sda",
  "tag:dm",
  "startmap:dmc2m1",
  "startmap:dmc2m2",
  "startmap:dmc2m3",
  "startmap:dmc2m4",
  "startmap:dmc2m5"
 ],
 "install": {
  "extract": "{quake}/id1/maps"
 },
 "files": {
  "dmc2.txt": {
   "size": 1572,
   "timestamp": "2011-05-12"
  },
  "dmc2m1.bsp": {
   "size": 1223168,
   "timestamp": "2011-05-24"
  },
  "dmc2m2.bsp": {
   "size": 1459980,
   "timestamp": "2011-05-24"
  },
  "dmc2m3.bsp": {
   "size": 1090268,
   "timestamp": "2011-05-24"
  },
  "dmc2m4.bsp": {
   "size": 1609728,
   "timestamp": "2011-05-24"
  },
  "dmc2m5.bsp": {
   "size": 1484876,
   "timestamp": "2011-05-24"
  }
 },
 "urls": [
  "https://www.quaddicted.com/filebase/dmc2.zip",
  "https://www.quaddicted.com/files/by-sha256/c/c9b7c8c78b0808972a2ca7055df3ba1898f8004d1cc34f09ae1f0f9042889a4e/dmc2.zip"
 ]
}