{
 "version": "20191222-0",
 "md5": "0b908525c1a9ca5ead173ddec390fb02",
 "filename": [
  "dspirl11.zip"
 ],
 "size": 629,
 "releasedate": "1996-12-27",
 "tags": [
  "title:The Downward Spiral",
  "author:Stan C.",
  "tag:metal",
  "tag:wizard",
  "tag:bridge",
  "tag:waterfall",
  "tag:temple",
  "tag:caverns",
  "tag:medium",
  "tag:canyon",
  "tag:traps"
 ],
 "install": {
  "extract": "{quake}/id1/maps/"
 },
 "files": {
  "dspirl11.bsp": {
   "size": 1519408,
   "timestamp": "1996-12-27"
  },
  "dspirl11.txt": {
   "size": 5564,
   "timestamp": "1996-12-27"
  }
 }
}