{
 "version": "20191222-0",
 "md5": "76ce9c675aec7e5b4e41e5ed550dc49b",
 "filename": [
  "evildead.zip"
 ],
 "size": 489,
 "releasedate": "1997-10-20",
 "tags": [
  "title:EvilDead cabin",
  "author:Steve Rescoe",
  "tag:small",
  "tag:wood",
  "tag:house",
  "tag:forest",
  "tag:source",
  "tag:realism"
 ],
 "install": {
  "extract": "{quake}/id1/maps/"
 },
 "files": {
  "Evildead.map": {
   "size": 362504,
   "timestamp": "1997-10-19"
  },
  "evildead.txt": {
   "size": 2528,
   "timestamp": "1997-10-20"
  },
  "evildead.bsp": {
   "size": 1159392,
   "timestamp": "1997-10-20"
  }
 }
}