{
 "version": "20191222-0",
 "md5": "c83c6f2ee3f38e25cc576319fde05a10",
 "filename": [
  "flecksp1.zip"
 ],
 "size": 516,
 "releasedate": "2004-03-12",
 "tags": [
  "title:Azure Influx",
  "author:Justin Fleck",
  "tag:medium",
  "tag:metal",
  "tag:textures",
  "tag:bw",
  "tag:speedrunning",
  "tag:hard"
 ],
 "install": {
  "extract": "{quake}/id1/maps/"
 },
 "files": {
  "flecksp1.bsp": {
   "size": 1315616,
   "timestamp": "2004-03-12"
  },
  "flecksp1.txt": {
   "size": 1158,
   "timestamp": "2004-03-12"
  }
 }
}