{
 "version": "20191222-0",
 "md5": "a448a0066a648e6eb59ce551044be4bc",
 "filename": [
  "jason1.zip"
 ],
 "size": 1235,
 "releasedate": "2002-01-27",
 "tags": [
  "title:Jason's first map pack",
  "author:Grey Fox (Jason)",
  "tag:medium",
  "tag:wizard",
  "tag:mixed"
 ],
 "install": {
  "extract": "{quake}/id1/maps/"
 },
 "files": {
  "jason.txt": {
   "size": 1458,
   "timestamp": "2002-01-26"
  },
  "JASON1.bsp": {
   "size": 1084136,
   "timestamp": "1999-09-07"
  },
  "JASON2.bsp": {
   "size": 872180,
   "timestamp": "2002-01-27"
  },
  "jason3.bsp": {
   "size": 1040716,
   "timestamp": "2002-01-26"
  }
 }
}