{
 "version": "20191222-0",
 "md5": "68a86ec8fe5005661f5b212aa5cf448b",
 "filename": [
  "kjsp1.zip"
 ],
 "size": 1442,
 "releasedate": "2001-10-13",
 "tags": [
  "title:Avanipaala Praasaada (Palace of the Great Warriors)",
  "author:Killjoy",
  "tag:ikwhite",
  "tag:palace",
  "tag:large",
  "tag:asian",
  "tag:bright",
  "tag:planetquake-map-of-the-week"
 ],
 "install": {
  "extract": "{quake}/id1/maps/"
 },
 "files": {
  "kjsp1.bsp": {
   "size": 3348084,
   "timestamp": "2001-10-13"
  },
  "kjsp1.txt": {
   "size": 6228,
   "timestamp": "2001-10-13"
  }
 }
}