{
 "version": "20191222-0",
 "md5": "f832be5e6ba2f1763440eb4706cb149c",
 "filename": [
  "matsp2.zip"
 ],
 "size": 1820,
 "releasedate": "2003-04-21",
 "tags": [
  "title:Best of Vize",
  "author:Mateusz 'MaTi' Piaskiewicz",
  "tag:q2base",
  "tag:quake2",
  "tag:medium"
 ],
 "install": {
  "extract": "{quake}/id1/"
 },
 "files": {
  "maps/matsp2.txt": {
   "size": 1910,
   "timestamp": "2003-04-21"
  },
  "maps/matsp2.lit": {
   "size": 1894409,
   "timestamp": "2003-04-20"
  },
  "maps/matsp2.bsp": {
   "size": 3780248,
   "timestamp": "2003-04-20"
  },
  "matsp2_quaddictedrepack.txt": {
   "size": 319,
   "timestamp": "2009-04-28"
  },
  "gfx/env/vlcnodn.tga": {
   "size": 196944,
   "timestamp": "1999-06-30"
  },
  "gfx/env/vlcnolf.tga": {
   "size": 196944,
   "timestamp": "1999-06-30"
  },
  "gfx/env/vlcnoup.tga": {
   "size": 196944,
   "timestamp": "1999-06-30"
  },
  "gfx/env/vlcnobk.tga": {
   "size": 196944,
   "timestamp": "1999-06-30"
  },
  "gfx/env/vlcnoft.tga": {
   "size": 196944,
   "timestamp": "1999-06-30"
  },
  "gfx/env/vlcnort.tga": {
   "size": 196944,
   "timestamp": "1999-06-30"
  }
 }
}