{
 "version": "20191222-0",
 "md5": "ad3f0c9446cd81d2ba7a8234e3e74ca6",
 "filename": [
  "nar_vault.zip"
 ],
 "size": 1577,
 "releasedate": "2015-11-25",
 "tags": [
  "title:In the Foetid Vault",
  "author:nadzia (narnar)",
  "tag:bw"
 ],
 "install": {
  "extract": "{quake}/id1/maps/"
 },
 "files": {
  "nar_vault.bsp": {
   "size": 3161092,
   "timestamp": "2015-11-26"
  },
  "nar_vault.lit": {
   "size": 1206920,
   "timestamp": "2015-11-26"
  },
  "nar_vault.txt": {
   "size": 4585,
   "timestamp": "2015-11-26"
  }
 }
}