{
 "version": "20191222-0",
 "md5": "589dc3c87392ca482538bdda4fe0df0f",
 "filename": [
  "retrojam4dlc_pulsar.zip"
 ],
 "size": 3460,
 "releasedate": "2016-02-14",
 "tags": [
  "title:The Elder Reality",
  "author:PuLSaR",
  "tag:medium",
  "tag:medieval",
  "tag:remix",
  "tag:remake",
  "tag:secrets",
  "tag:spanws",
  "tag:dark",
  "tag:hard",
  "tag:multiple exits",
  "tag:spawn",
  "tag:e4"
 ],
 "install": {
  "extract": "{quake}/id1/maps/"
 },
 "files": {
  "retrojam4dlc_pulsar.bsp": {
   "size": 7863880,
   "timestamp": "2016-02-14"
  },
  "retrojam4dlc_pulsar.lit": {
   "size": 3071948,
   "timestamp": "2016-02-14"
  },
  "retrojam4dlc_pulsar.txt": {
   "size": 7950,
   "timestamp": "2016-02-14"
  }
 }
}