{
 "version": "20191222-0",
 "md5": "d8e16ac5058823d80ff7b56352783d55",
 "filename": [
  "sm196_pack.zip"
 ],
 "size": 11724,
 "releasedate": "2019-05-07",
 "tags": [
  "title:Speedmapping pack 196 - Quick Honey",
  "author:Artistical",
  "author:Danzadan",
  "author:Fairweather",
  "author:Mazu",
  "author:Ing-Ing",
  "author:Muk",
  "author:Pinchy",
  "author:Yoder"
 ],
 "install": {
  "extract": "{quake}/id1/"
 },
 "files": {
  "maps/sm196_artistical.bsp": {
   "size": 3833812,
   "timestamp": "2019-05-05"
  },
  "maps/sm196_danz.bsp": {
   "size": 2364528,
   "timestamp": "2019-05-06"
  },
  "maps/sm196_fairweather.bsp": {
   "size": 6043464,
   "timestamp": "2019-05-06"
  },
  "maps/sm196_fairweather.lit": {
   "size": 2111474,
   "timestamp": "2019-05-06"
  },
  "maps/sm196_hcm.bsp": {
   "size": 7402636,
   "timestamp": "2019-05-05"
  },
  "maps/sm196_hcm.lit": {
   "size": 1812617,
   "timestamp": "2019-05-05"
  },
  "maps/sm196_ing.bsp": {
   "size": 1053796,
   "timestamp": "2019-05-05"
  },
  "maps/sm196_muk.bsp": {
   "size": 2570112,
   "timestamp": "2019-05-06"
  },
  "maps/sm196_muk.lit": {
   "size": 922736,
   "timestamp": "2019-05-06"
  },
  "maps/sm196_pinchy.bsp": {
   "size": 1129140,
   "timestamp": "2019-05-05"
  },
  "maps/sm196_pinchy.lit": {
   "size": 356567,
   "timestamp": "2019-05-05"
  },
  "maps/sm196_yoder.bsp": {
   "size": 2446944,
   "timestamp": "2019-05-05"
  },
  "maps/sm196_yoder.lit": {
   "size": 1221347,
   "timestamp": "2019-05-05"
  },
  "sm196_Readme.txt": {
   "size": 697,
   "timestamp": "2019-05-07"
  },
  "sm196_hcm.txt": {
   "size": 1927,
   "timestamp": "2019-05-05"
  },
  "sm196_pinchy.txt": {
   "size": 2530,
   "timestamp": "2019-05-05"
  },
  "source/sm196_artistical.map": {
   "size": 1626788,
   "timestamp": "2019-05-05"
  },
  "source/sm196_danz.map": {
   "size": 1597226,
   "timestamp": "2019-05-06"
  },
  "source/sm196_hcm.map": {
   "size": 3094251,
   "timestamp": "2019-05-05"
  },
  "source/sm196_ing.map": {
   "size": 243635,
   "timestamp": "2019-05-05"
  },
  "source/sm196_pinchy.map": {
   "size": 556967,
   "timestamp": "2019-05-05"
  },
  "source/sm196_yoder.map": {
   "size": 2400467,
   "timestamp": "2019-05-05"
  },
  "yoderReadme.txt": {
   "size": 1882,
   "timestamp": "2019-05-05"
  }
 }
}