{
 "version": "20191222-0",
 "md5": "6d8e1ee6110fc40684c9dd561cfd5091",
 "filename": [
  "sm81_pack.zip"
 ],
 "size": 1283,
 "releasedate": "2004-06-06",
 "tags": [
  "title:Speedmapping pack 81 - Massive Scale",
  "author:Paintsniffing Joe",
  "author:Speedy",
  "author:Starbuck",
  "author:Zwiffle",
  "tag:spd"
 ],
 "install": {
  "extract": "{quake}/id1/maps/"
 },
 "files": {
  "sm81_pack.txt": {
   "size": 1475,
   "timestamp": "2004-03-21"
  },
  "sm81_speedy.bsp": {
   "size": 1347256,
   "timestamp": "2004-06-06"
  },
  "sm81_starbuck.bsp": {
   "size": 523308,
   "timestamp": "2004-06-06"
  },
  "sm81_zwiffle.bsp": {
   "size": 449892,
   "timestamp": "2004-06-05"
  },
  "sm81_paintyj.bsp": {
   "size": 1570048,
   "timestamp": "2004-06-05"
  }
 }
}