{
 "bytes": 581,
 "files": {
  "MEXX5.BSP": {
   "bytes": 1440804,
   "sha256": "8f63b83ef47cf4830eaa6277bd798611dbf045b0b4614ab519c1756f4a76316a",
   "timestamp": "1997-02-03T19:20:26.000Z"
  },
  "MEXX5.TXT": {
   "bytes": 3120,
   "sha256": "69b69ca474012d5d0e4557103f8d29626044bf4eac5238d4d8ff77d085ac78d1",
   "timestamp": "1997-02-03T20:19:26.000Z"
  }
 },
 "install": {
  "extract": "{base}/id1/maps/"
 },
 "json_version": "2023.01.02-22.55",
 "sha256": "0abccd5b0080bffc3e24f2409bf018cf4e07dc144e854314b7a58e8daa8e8aef",
 "tags": [
  "author=Marcus Dromowicz",
  "filename=mexx5.zip",
  "game=quake",
  "game_mode=deathmatch",
  "game_mode=singleplayer",
  "link=[Crash's](http://www.quake2.com/crash/levelsm1.htm#mexx5)",
  "link=[Geniac's Playlist](http://www.geniac.net/quake.htm)",
  "link=[TEAMShambler](/webarchive/teamshambler.planetquake.gamespy.com/list.html)",
  "map_size=large",
  "release_date=1997-02-03",
  "theme=lava",
  "theme=metal",
  "theme=traps",
  "title=The Terror of Tzeentch",
  "type=map"
 ],
 "urls": [
  "https://www.quaddicted.com/filebase/mexx5.zip",
  "https://www.quaddicted.com/files/by-sha256/0/0abccd5b0080bffc3e24f2409bf018cf4e07dc144e854314b7a58e8daa8e8aef/mexx5.zip"
 ]
}