{
 "filename": [
  "btf2.zip"
 ],
 "files": {
  "btf2.bsp": {
   "sha256": "48338ff6e88b0c83b9db377da9f810bc8a14f6ab07aaf9d07e4136816ae84871",
   "size": 1400168,
   "timestamp": "1997-02-04T15:07:22.000Z"
  },
  "btf2.txt": {
   "sha256": "45c82897a655d0f4d6a9c1e7c10a0388de5beaa0e2c4c7424964f77783a6fed6",
   "size": 2835,
   "timestamp": "1997-02-03T20:08:06.000Z"
  }
 },
 "filesize": 604,
 "install": {
  "extract": "{quake}/id1/maps/"
 },
 "json_version": "2019.12.24-12.08",
 "sha256": "0c17dbf82b39e14c517fbd8daa791de8ab3a7c4225a175dae87f25e08d7a390c",
 "tags": [
  "author=Rob Albin",
  "game=quake",
  "link=[Crash's](http://www.quake2.com/crash/levelsb.htm#btf2)",
  "releasedate=1997-02-03",
  "tag=exploration",
  "tag=large",
  "tag=medieval",
  "tag=medium",
  "tag=puzzles",
  "tag=traps",
  "title=Bridge to Fire"
 ],
 "urls": [
  "https://www.quaddicted.com/filebase/btf2.zip",
  "https://www.quaddicted.com/files/by-sha256/0/0c17dbf82b39e14c517fbd8daa791de8ab3a7c4225a175dae87f25e08d7a390c/btf2.zip"
 ]
}