{
 "bytes": 552,
 "files": {
  "undrwrld.bsp": {
   "bytes": 1330788,
   "sha256": "14f319a536bbb76e0434f8d19f0df1ca325841972cc0937c1cd171db54bf809b",
   "timestamp": "1997-01-11T03:01:16.000Z"
  },
  "undrwrld.txt": {
   "bytes": 4032,
   "sha256": "6527b366317636f052a3674ae47a1eb2699d2be3f51a897472b7d11d4c14e4cd",
   "timestamp": "1997-01-11T12:29:50.000Z"
  }
 },
 "install": {
  "extract": "{base}/id1/maps/"
 },
 "json_version": "2023.11.06-23.20",
 "sha256": "a69d7f5239df0b9695636b9ada4433944e4598413ebfb28627f847170b647a9a",
 "tags": [
  "author=Matt Sefton",
  "filename=undrwrld.zip",
  "game=quake",
  "game_mode=deathmatch",
  "game_mode=singleplayer",
  "link=[Crash's](http://www.quake2.com/crash/levelsu.htm#undrwrld)",
  "link=[Retroquake](http://retroquake.planetquake.gamespy.com/blog/?p=82)",
  "link=[SPQ Level Heaven](/webarchive/hosted.planetquake.gamespy.com/spq2/quake1/s_u.htm)",
  "link=[TEAMShambler](/webarchive/teamshambler.planetquake.gamespy.com/list.html)",
  "map_size=small",
  "release_date=1997-01-11",
  "theme=base",
  "theme=outdoor",
  "theme=traps",
  "title=The Underworld",
  "type=map"
 ],
 "urls": [
  "https://www.quaddicted.com/filebase/undrwrld.zip",
  "https://www.quaddicted.com/files/by-sha256/a6/a69d7f5239df0b9695636b9ada4433944e4598413ebfb28627f847170b647a9a/undrwrld.zip"
 ]
}
