{
 "filename": [
  "sm200_pack.zip"
 ],
 "files": {
  "maps/sm200a.bsp": {
   "filesize": 5064748,
   "timestamp": "2019-08-18"
  },
  "maps/sm200a.lit": {
   "filesize": 3187172,
   "timestamp": "2019-08-18"
  },
  "maps/sm200a.map": {
   "filesize": 2366321,
   "timestamp": "2019-08-18"
  },
  "maps/sm200b.bsp": {
   "filesize": 4639456,
   "timestamp": "2019-08-18"
  },
  "maps/sm200b.lit": {
   "filesize": 2803136,
   "timestamp": "2019-08-18"
  },
  "maps/sm200b.map": {
   "filesize": 2584487,
   "timestamp": "2019-08-18"
  },
  "maps/sm200c.bsp": {
   "filesize": 8201408,
   "timestamp": "2019-08-18"
  },
  "maps/sm200c.lit": {
   "filesize": 5008118,
   "timestamp": "2019-08-18"
  },
  "maps/sm200c.map": {
   "filesize": 7511176,
   "timestamp": "2019-08-18"
  },
  "maps/sm200d.bsp": {
   "filesize": 13339992,
   "timestamp": "2019-08-18"
  },
  "maps/sm200d.lit": {
   "filesize": 4491368,
   "timestamp": "2019-08-18"
  },
  "maps/sm200d.map": {
   "filesize": 6437424,
   "timestamp": "2019-08-18"
  },
  "sm200_pack.txt": {
   "filesize": 1883,
   "timestamp": "2019-08-18"
  }
 },
 "filesize": 18146,
 "install": {
  "extract": "{quake}/id1/"
 },
 "json_version": "2019.12.24-11.15",
 "sha256": "9724bff7f8e23d2a49cab2b95118595b8b897c3a31075b30a46e33c04b142698",
 "tags": [
  "author=Artistical",
  "author=Fairweather",
  "author=JCR",
  "author=MortalMaxx",
  "author=Mugwump",
  "author=Pinchy Skree",
  "author=Ukko",
  "author=Vurkka",
  "author=Zungryware",
  "author=ionous",
  "author=onetruepurple",
  "game=quake",
  "link=[Func_Msgboard](http://celephais.net/board/view_thread.php?id=61762)",
  "link=[Screenshot poster](http://www.quaketastic.com/files/single_player/speed_maps/sm200.jpg)",
  "releasedate=2019-08-18",
  "startmap=sm200a",
  "startmap=sm200b",
  "startmap=sm200c",
  "startmap=sm200d",
  "title=SM200: Chainmap Chaos"
 ],
 "urls": [
  "https://www.quaddicted.com/filebase/sm200_pack.zip",
  "https://www.quaddicted.com/files/by-sha256/9/9724bff7f8e23d2a49cab2b95118595b8b897c3a31075b30a46e33c04b142698/sm200_pack.zip"
 ]
}