{
 "filename": [
  "lpqsp1.zip"
 ],
 "files": {
  "lpqsp1.bsp": {
   "filesize": 5185760,
   "timestamp": "2016-09-20"
  },
  "lpqsp1.lit": {
   "filesize": 4289102,
   "timestamp": "2016-09-20"
  },
  "lpqsp1.txt": {
   "filesize": 1546,
   "timestamp": "2016-09-19"
  }
 },
 "filesize": 2820,
 "install": {
  "extract": "{quake}/quoth/maps/"
 },
 "json_version": "2019.12.24-11.15",
 "sha256": "50105e2a0c4ffa3d035a39c705b76d1791716db9e70fe25062e106037a2317f0",
 "tags": [
  "author=Lane Powell",
  "commandline=-game quoth -quoth",
  "dependency=quoth2pt2full_2",
  "game=quake",
  "link=[Func_Msgboard](http://celephais.net/board/view_thread.php?id=61353)",
  "releasedate=2016-09-19",
  "startmap=lpqsp1",
  "tag=blood",
  "tag=blue",
  "tag=large",
  "tag=limits",
  "tag=metal",
  "tag=quoth",
  "tag=secrets",
  "tag=void",
  "title=The Bonehoard"
 ],
 "urls": [
  "https://www.quaddicted.com/filebase/lpqsp1.zip",
  "https://www.quaddicted.com/files/by-sha256/5/50105e2a0c4ffa3d035a39c705b76d1791716db9e70fe25062e106037a2317f0/lpqsp1.zip"
 ]
}