{
 "filename": [
  "ananke.zip"
 ],
 "files": {
  "ananke.bsp": {
   "filesize": 2738108,
   "timestamp": "2006-04-24"
  },
  "ananke.txt": {
   "filesize": 1787,
   "timestamp": "2006-04-26"
  }
 },
 "filesize": 1005,
 "install": {
  "extract": "{quake}/id1/maps/"
 },
 "sha256": "5d49c668d8ea67bf4239f0c58ecf9ab0488b24281b775ad4b725b48f7be8c2f0",
 "tags": [
  "title:Ananke 17",
  "releasedate:2006-04-26",
  "game:quake",
  "author:Ankh",
  "tag:base",
  "tag:quake2",
  "tag:cave",
  "tag:small",
  "tag:space",
  "tag:void"
 ],
 "urls": [
  "https://www.quaddicted.com/filebase/ananke.zip",
  "https://www.quaddicted.com/files/by-sha256/5/5d49c668d8ea67bf4239f0c58ecf9ab0488b24281b775ad4b725b48f7be8c2f0/ananke.zip"
 ],
 "version": "20191222-0"
}