{
 "filename": [
  "frcastl2.zip"
 ],
 "files": {
  "frcastl2.TXT": {
   "filesize": 916,
   "timestamp": "1996-10-30"
  },
  "frcastl2.bsp": {
   "filesize": 884008,
   "timestamp": "1996-10-30"
  }
 },
 "filesize": 363,
 "install": {
  "extract": "{quake}/id1/maps/"
 },
 "json_version": "2019.12.24-11.15",
 "sha256": "6121e8de462e724b6919387ff8ad8e5da9541a1786bd6f14a6e31675ca09aeea",
 "tags": [
  "author=Robert Carter",
  "game=quake",
  "link=[Crash's](http://www.quake2.com/crash/levelsf.htm#fcastle)",
  "link=[SPQ Level Heaven](/webarchive/hosted.planetquake.gamespy.com/spq2/quake1/d_f.htm)",
  "releasedate=1996-10-30",
  "tag=castle",
  "tag=dark",
  "tag=dm",
  "tag=small",
  "tag=wizard",
  "title=Fear Castle v.2"
 ],
 "urls": [
  "https://www.quaddicted.com/filebase/frcastl2.zip",
  "https://www.quaddicted.com/files/by-sha256/6/6121e8de462e724b6919387ff8ad8e5da9541a1786bd6f14a6e31675ca09aeea/frcastl2.zip"
 ]
}