{
 "filename": [
  "borax3.zip"
 ],
 "files": {
  "BORAX3.TXT": {
   "size": 5916,
   "timestamp": "1998-12-31T11:46:44.000Z"
  },
  "Borax3.bsp": {
   "size": 2477600,
   "timestamp": "1998-12-24T17:44:42.000Z"
  }
 },
 "filesize": 1061,
 "install": {
  "extract": "{quake}/id1/maps/"
 },
 "json_version": "2019.12.24-13.03",
 "sha256": "41f7f95f1a87bdd39f2b1f90c09ef0fa54050cca25c09bdd361b77918f16e6ac",
 "tags": [
  "author=Dennis Katsonis",
  "game=quake",
  "releasedate=1998-12-31",
  "tag=large",
  "tag=wizard",
  "title=Borax 3"
 ],
 "urls": [
  "https://www.quaddicted.com/filebase/borax3.zip",
  "https://www.quaddicted.com/files/by-sha256/4/41f7f95f1a87bdd39f2b1f90c09ef0fa54050cca25c09bdd361b77918f16e6ac/borax3.zip"
 ]
}