{
 "filename": [
  "techdeth.zip"
 ],
 "files": {
  "techdeth.bsp": {
   "size": 1031224,
   "timestamp": "1997-09-03T08:24:14.000Z"
  }
 },
 "filesize": 430,
 "install": {
  "extract": "{quake}/id1/maps/"
 },
 "json_version": "2019.12.24-13.03",
 "sha256": "e07d347dcde150d0551e8f2f192d195ab9eea11ef59d5422c56b6f031fd82a70",
 "tags": [
  "author=Unknown",
  "game=quake",
  "releasedate=1997-09-03",
  "tag=base",
  "tag=dark",
  "tag=small",
  "title=Tech Death"
 ],
 "urls": [
  "https://www.quaddicted.com/filebase/techdeth.zip",
  "https://www.quaddicted.com/files/by-sha256/e/e07d347dcde150d0551e8f2f192d195ab9eea11ef59d5422c56b6f031fd82a70/techdeth.zip"
 ]
}