{
 "filename": [
  "rdestats161.zip"
 ],
 "files": {
  "PAK1.PAK": {
   "filesize": 509691,
   "timestamp": "2000-03-30"
  },
  "RDESTATS.TXT": {
   "filesize": 2174,
   "timestamp": "2000-03-30"
  }
 },
 "filesize": 153,
 "install": {
  "extract": "{quake}/rde/"
 },
 "json_version": "2019.12.23-20.57",
 "sha256": "d2489b4b26e65b81676112dcbed4eac2eb87f017f0f3de18b871e357da3b0bad",
 "tags": [
  "title=Runner's Delight (BUGFIX)",
  "releasedate=2000-03-30",
  "game=quake",
  "author=Jesse van Dijk"
 ],
 "urls": [
  "https://www.quaddicted.com/filebase/rdestats161.zip",
  "https://www.quaddicted.com/files/by-sha256/d/d2489b4b26e65b81676112dcbed4eac2eb87f017f0f3de18b871e357da3b0bad/rdestats161.zip"
 ]
}