{
 "bytes": 1966,
 "files": {
  "sm79_drew.bsp": {
   "bytes": 859772,
   "sha256": "b478f6c642adf4c222648a7d914600ff9bf5a318c962822e7e38717b7b63ba61",
   "timestamp": "2004-04-13T01:00:10.000Z"
  },
  "sm79_fmb.bsp": {
   "bytes": 1540776,
   "sha256": "a3e7229073812024f1e5fa9e7ead8afb6e31bac5eb601bb23cc0dd98df7e2b8d",
   "timestamp": "2004-05-09T07:48:10.000Z"
  },
  "sm79_necros.bsp": {
   "bytes": 503572,
   "sha256": "d9be8550dee04278c9d507cda6e0e5c184e5a7b2254017977927e6342db70d7b",
   "timestamp": "2004-05-22T17:47:48.000Z"
  },
  "sm79_pack.txt": {
   "bytes": 1619,
   "sha256": "60f9c9f54db870a1d1a9e80247757974b23b0d6b1e27e4c7a914b2ab6cae664c",
   "timestamp": "2004-03-22T18:34:18.000Z"
  },
  "sm79_rpg.bsp": {
   "bytes": 286564,
   "sha256": "af9aac0aba7aa1292bb7746f7f71bece5092600a2b83611a7802df94cfa6d259",
   "timestamp": "2004-03-22T13:52:16.000Z"
  },
  "sm79_scampie.bsp": {
   "bytes": 705936,
   "sha256": "7f6f81beb4931475ae478f37ef873a25c0cf7a8037f795d30536323f13af0577",
   "timestamp": "2004-03-22T18:16:20.000Z"
  },
  "sm79_zwiffle.bsp": {
   "bytes": 1121504,
   "sha256": "48c82830ea82bf473e0e0869e9da9140ea36089612f4cb88c87c16955eb30b94",
   "timestamp": "2004-05-22T17:24:00.000Z"
  }
 },
 "install": {
  "extract": "{base}/id1/maps/"
 },
 "json_version": "2023.01.02-22.55",
 "sha256": "d46ea4a316b3b6744aeed2c2a70bea73237e9ddb2836fcf9019f5c96ce1b4d5d",
 "tags": [
  "author=Drew",
  "author=Mike Woodham",
  "author=RPG",
  "author=Scampie",
  "author=Zwiffle",
  "author=necros",
  "filename=sm79_pack.zip",
  "game=quake",
  "game_mode=singleplayer",
  "release_date=2004-05-22",
  "startmap=sm79_drew",
  "startmap=sm79_fmb",
  "startmap=sm79_necros",
  "startmap=sm79_rpg",
  "startmap=sm79_scampie",
  "startmap=sm79_zwiffle",
  "title=Speedmapping pack 79 - Abandoned city",
  "type=speedmap"
 ],
 "urls": [
  "https://www.quaddicted.com/filebase/sm79_pack.zip",
  "https://www.quaddicted.com/files/by-sha256/d/d46ea4a316b3b6744aeed2c2a70bea73237e9ddb2836fcf9019f5c96ce1b4d5d/sm79_pack.zip"
 ]
}
